formair/__init__.py
formair/formair.py
formair/forward.py
formair/pop3.py
formair/smtp.py
formair/utils.py
formair-1.3.1.dist-info/LICENSE
formair-1.3.1.dist-info/METADATA
formair-1.3.1.dist-info/WHEEL
formair-1.3.1.dist-info/entry_points.txt
formair-1.3.1.dist-info/top_level.txt
formair-1.3.1.dist-info/RECORD
