Metadata-Version: 2.1
Name: formair
Version: 1.3.1
Summary: auto Forward eMails with custom Rules
Home-page: https://github.com/k8scat/ForMaiR
Author: K8sCat
Author-email: k8scat@gmail.com
License: UNKNOWN
Platform: UNKNOWN
Classifier: Programming Language :: Python :: 3
Classifier: License :: OSI Approved :: MIT License
Classifier: Operating System :: OS Independent
Requires-Python: >=3.6
Requires-Dist: PyYaml
